{
  "stocks_traderfox_us_healthcare": {
    "name": "TraderFox US Healthcare Portfolio",
    "description": "US Healthcare sector stocks based on TraderFox research covering pharmaceuticals, biotechnology, medical devices, healthcare services, and digital health companies",
    "asset_type": "stock",
    "symbols": [
      "JNJ",
      "PFE",
      "UNH",
      "MRK",
      "ABBV",
      "TMO",
      "DHR",
      "ABT",
      "BMY",
      "LLY",
      "GILD",
      "AMGN",
      "BIIB",
      "REGN",
      "VRTX",
      "ZTS",
      "CVS",
      "CI",
      "HUM",
      "ANTM",
      "MCK",
      "ABC",
      "CAH",
      "WBA",
      "MDT",
      "ISRG",
      "SYK",
      "BSX",
      "BDX",
      "EW",
      "ZBH",
      "BAX",
      "HOLX",
      "IDXX",
      "ALGN",
      "DXCM",
      "RMD",
      "ILMN",
      "MKTX",
      "VEEV",
      "TDOC",
      "DOCU",
      "HIMS",
      "ONEM",
      "AMWL",
      "OSCR",
      "WELL",
      "MRNA",
      "BNTX",
      "NVAX",
      "OCGN",
      "INO",
      "SRNE",
      "VXRT",
      "GEVO",
      "CODX",
      "QDEL",
      "DVAX",
      "IOVA",
      "TXMD",
      "CERC",
      "ADVM",
      "DARE",
      "KERN",
      "XERS",
      "ATOS",
      "CTMX",
      "PROG",
      "ADMA",
      "SESN",
      "AXSM",
      "PTCT",
      "ALNY",
      "BMRN",
      "TECH",
      "RARE",
      "FOLD",
      "BLUE",
      "CRSP",
      "EDIT",
      "NTLA",
      "BEAM",
      "VERV",
      "SGMO",
      "FATE",
      "BLFS",
      "CDNA",
      "ARCT",
      "DMTK",
      "VCYT",
      "PACB",
      "NVTA",
      "TWST",
      "NTRA",
      "GH",
      "CDXS",
      "AGIO",
      "ARQL",
      "APLS",
      "AVXL",
      "CBIO",
      "ACAD",
      "HZNP",
      "JAZZ",
      "UTHR",
      "NBIX",
      "SAGE",
      "INCY",
      "EXEL",
      "BGNE",
      "ZLAB",
      "RGNX",
      "IMMU",
      "SGEN",
      "BPMC",
      "MRUS",
      "CPRX",
      "VCEL",
      "CAPR",
      "MEDP",
      "VKTX",
      "ACLX",
      "NVCR",
      "TMDX",
      "VECO",
      "BHVN",
      "AOSL",
      "CELH",
      "SEZL",
      "ALLO",
      "PRAX",
      "RCAT",
      "OTLK",
      "CENX",
      "PSNL",
      "NSIT",
      "CHRS",
      "SIGA",
      "ACIU",
      "PERI",
      "STNE",
      "LILA",
      "ALTI",
      "INDV",
      "CEVA",
      "SPNS",
      "CFB",
      "LWAY",
      "CRBP",
      "FEIM",
      "PLAB",
      "DSP",
      "PNTG",
      "IDYA",
      "ENTG",
      "RMBS",
      "TSAT",
      "HALO",
      "OMER",
      "ADUS",
      "LMAT",
      "FELE",
      "APOG",
      "CRL",
      "CBLL",
      "COOP",
      "CHDN",
      "ENSG",
      "DGX",
      "KYMR",
      "CSTL",
      "TREE",
      "SNEX",
      "CCB",
      "OSIS",
      "PLMR",
      "CASY",
      "LECO",
      "HLNE",
      "UFPT",
      "ERIE",
      "MOH",
      "ITIC",
      "PIPR",
      "FCNCA",
      "VIRT",
      "NARI",
      "ALGT",
      "RKLB",
      "IONQ",
      "FUTU",
      "BABA",
      "ULTA",
      "DOCS",
      "UNFI",
      "BIDU",
      "ROKU",
      "TTAN",
      "LNTH",
      "TTMI",
      "BYRN",
      "GRAB",
      "EH",
      "ASTS",
      "DOCN",
      "SMPL",
      "PGY",
      "FRHC",
      "ETON",
      "AKRO",
      "MRCY",
      "RDNT",
      "ARDX",
      "AMAT",
      "TTD",
      "DKNG",
      "DASH",
      "TEVA",
      "DBX",
      "CROX",
      "CORT",
      "AXON",
      "TXRH",
      "ABNB",
      "AFRM",
      "NET",
      "TZOO",
      "EXLS",
      "SOUN",
      "CRWD",
      "IBKR",
      "AHCO",
      "ENVX",
      "SOFI",
      "APPF",
      "TLN",
      "FLEX",
      "TEM",
      "ME",
      "EBAY",
      "AUR",
      "TATT",
      "SPSC",
      "ALAB",
      "PRCH",
      "UPST",
      "SYM",
      "LRCX",
      "APLT",
      "MARA",
      "RGTI",
      "ZI",
      "SNOW",
      "RDVT",
      "CDNS",
      "SMWB",
      "DTSS",
      "TSLA",
      "UFPI",
      "AVGO",
      "VRNS",
      "MSFT",
      "ARM",
      "IMNM",
      "GERN",
      "VTSI",
      "LUNR",
      "MELI",
      "APPN",
      "ALVO",
      "LRN",
      "CMG",
      "MORN",
      "APH",
      "QCOM",
      "BAH",
      "SCCO",
      "TNC",
      "NTNX",
      "KLAC",
      "FCX",
      "QLYS",
      "HOOD",
      "MAR",
      "PCAR",
      "KRUS",
      "TDW",
      "PWR",
      "PDD",
      "XMTR",
      "MSTR",
      "GCT",
      "FOR",
      "LFMD",
      "BKNG",
      "APGE",
      "ROAD",
      "APP",
      "ARVN",
      "TNDM",
      "CGON",
      "ADPT",
      "TRUP",
      "CWST",
      "SCHW",
      "CALX",
      "FSLR",
      "PI",
      "KAI",
      "HWKN",
      "INTU",
      "PSMT",
      "FCFS",
      "MGRC",
      "COKE",
      "DORM",
      "LOPE",
      "COST",
      "CVCO",
      "HESM",
      "TDY",
      "ANSS",
      "IPAR",
      "CSWI",
      "YELP",
      "ATRO",
      "AIOT",
      "ARQT",
      "INTA",
      "ATAT",
      "MTSR",
      "ANGO",
      "RR",
      "ALHC",
      "SLNO",
      "PDEX",
      "RGLD",
      "OPOF",
      "SENEB",
      "CME",
      "ORLY",
      "CRWV",
      "RYTM",
      "TARS",
      "WLFC",
      "FTAI",
      "AMSC"
    ],
    "initial_capital": 10000,
    "commission": 0.001
  }
}
